{
  "id": "edas-drs-8-5640",
  "source": "edas",
  "parliament": "sachsen",
  "wp": 8,
  "type": "antrag",
  "title": "Jugend schützen, Zusammenhalt stärken - Rechtsradikalisierung junger Menschen in Sachsen entschieden entgegentreten",
  "date": "2026-01-20",
  "drsNr": "8/5640",
  "persons": [],
  "fraktionen": [
    "bundnisgruene"
  ],
  "document": {
    "url": "https://redas.landtag.sachsen.de/redas/download?datei_id=47425",
    "filename": "Drs_8_5640_0.pdf"
  },
  "urheber": "BÜNDNISGRÜNE"
}
