{
  "id": "edas-drs-8-405",
  "source": "edas",
  "parliament": "sachsen",
  "wp": 8,
  "type": "antrag",
  "title": "Regierungsentwurf für das Sächsische Finanzausgleichsgesetz 2025/2026 vorlegen - Planungssicherheit für die Kommunen unverzüglich schaffen!",
  "date": "2024-11-12",
  "drsNr": "8/405",
  "persons": [],
  "fraktionen": [
    "afd"
  ],
  "document": {
    "url": "https://redas.landtag.sachsen.de/redas/download?datei_id=36831",
    "filename": "Drs_8_405_0.pdf"
  },
  "urheber": "AfD"
}
