{
  "id": "edas-drs-8-7055",
  "source": "edas",
  "parliament": "sachsen",
  "wp": 8,
  "type": "antrag",
  "title": "Kinderschutz in Schulen stärken - Verbindliche Schutzkonzepte einführen und Lehrkräftebildung qualifizieren",
  "date": "2026-05-21",
  "drsNr": "8/7055",
  "persons": [],
  "fraktionen": [
    "bundnisgruene",
    "die-linke"
  ],
  "document": {
    "url": "https://redas.landtag.sachsen.de/redas/download?datei_id=50889",
    "filename": "Drs_8_7055_0.pdf"
  },
  "urheber": "BÜNDNISGRÜNE, Die Linke"
}
