{
  "id": "parldok-drs-8-6238",
  "source": "parldok",
  "parliament": "mecklenburg-vorpommern",
  "wp": 8,
  "type": "antrag",
  "title": "Gesetz zur Änderung des Landesbeamtengesetzes, des Landesdisziplinargesetzes und des Landesbesoldungsgesetzes",
  "date": "2026-01-28",
  "drsNr": "8/6238",
  "persons": [],
  "fraktionen": [
    "fdp"
  ],
  "document": {
    "url": "https://www.dokumentation.landtag-mv.de/parldok/dokument/70230"
  },
  "subtype": "Änderungsantrag",
  "urheber": "FDP (Gruppe)"
}
